easy_ast/__init__.py
easy_ast/tensor_contract.py
easy_ast/utility.py
easy_ast-0.0.4.dist-info/LICENSE.rst
easy_ast-0.0.4.dist-info/METADATA
easy_ast-0.0.4.dist-info/WHEEL
easy_ast-0.0.4.dist-info/top_level.txt
easy_ast-0.0.4.dist-info/RECORD
