Metadata-Version: 2.1
Name: easy-ast
Version: 0.0.4
Summary: This package `easy-ast` contains several utility about AST transformer.
Author-email: Hao Zhang <hzhanxyz@outlook.com>
License: GNU GENERAL PUBLIC LICENSE
Project-URL: homepage, https://github.com/hzhangxyz/easy-ast
Project-URL: documentation, https://github.com/hzhangxyz/easy-ast
Project-URL: repository, https://github.com/hzhangxyz/easy-ast
Keywords: ast,macro
Requires-Python: >=3.10
License-File: LICENSE.rst
